toughlib/__init__.py
toughlib/alipay.py
toughlib/apiutils.py
toughlib/choosereactor.py
toughlib/config.py
toughlib/db_backup.py
toughlib/db_cache.py
toughlib/db_session.py
toughlib/dbengine.py
toughlib/dbutils.py
toughlib/dispatch.py
toughlib/httpclient.py
toughlib/logger.py
toughlib/mail.py
toughlib/mcache.py
toughlib/mputils.py
toughlib/paginator.py
toughlib/permit.py
toughlib/redis_cache.py
toughlib/redis_session.py
toughlib/storage.py
toughlib/taskd.py
toughlib/utils.py
toughlib/validate.py
toughlib/btforms/__init__.py
toughlib/btforms/dataform.py
toughlib/btforms/net.py
toughlib/btforms/rules.py
toughlib/tests/__init__.py
toughlib/tests/test_redis_cache.py
toughlib/tests/test_redis_session.py
toughlib-0.1.12.dist-info/DESCRIPTION.rst
toughlib-0.1.12.dist-info/METADATA
toughlib-0.1.12.dist-info/metadata.json
toughlib-0.1.12.dist-info/RECORD
toughlib-0.1.12.dist-info/top_level.txt
toughlib-0.1.12.dist-info/WHEEL
toughlib-0.1.12.dist-info/zip-safe
