Metadata-Version: 2.0
Name: toughlib
Version: 0.1.12
Summary: toughstruct python tools
Home-page: https://github.com/talkincode/toughlib
Author: jamiesun
Author-email: jamiesun.net@gmail.com
License: MIT
Keywords: toughstruct,toughradius
Platform: UNKNOWN
Classifier: Development Status :: 6 - Mature
Classifier: Intended Audience :: Developers
Classifier: Programming Language :: Python :: 2.6
Classifier: Programming Language :: Python :: 2.7
Classifier: Topic :: Software Development :: Libraries :: Python Modules
Requires-Dist: six (>=1.8.0)
Requires-Dist: Twisted (>=15.0.0)
Requires-Dist: SQLAlchemy
Requires-Dist: treq
